{"name":"GestIT","tagline":"A framework for reactive programming","body":"# GestIT JavaScript demos\r\n\r\n## Demos\r\n\r\n* [Draw+Pinch and Zoom](JavaScript/demo/SmartPaint.html)\r\n\r\n## Feature demos\r\n\r\n* [Show the trajectory of each touch](JavaScript/demo/UnboundTouch.html)\r\n* [Show the touches and a pinch](JavaScript/demo/UnboundTouchWithNaivePinchAndZoom.html)\r\n* [Show simultaneous tracking of touches and pinch](JavaScript/demo/UnboundTouchWithPinchAndZoom.html)\r\n* [Test the pinch and zoom gesture](JavaScript/demo/PinchAndZoom.html)\r\n\r\n## Utilities to test & debug multi-touch\r\n\r\n* [Multi-touch](JavaScript/test/multi.html)\r\n* [Drag and Drop](JavaScript/test/testDragAndDrop.html)\r\n\r\n# GestIT F# tutorials\r\n\r\nOn [TryF#](http://www.tryfsharp.org/) are available F# examples of the native version of GestIT:\r\n\r\n* [Drag and drop using GestIT](http://www.tryfsharp.org/create/cisterni/GestIT/tutorial/DragAndDrop.fsx)\r\n","google":"","note":"Don't delete this file! It's used internally to help with page regeneration."}